{
  "Id": "a7995d04-74fd-40dc-8443-4413c8d83ebb",
  "CategoryId": "0188e08a-8e5a-4ff7-9516-2024af36e9c2",
  "KeyName": "option_b",
  "Description": "",
  "CreatedAt": "2026-07-13T15:10:39.7165764Z",
  "UpdatedAt": "2026-07-13T20:00:11.108004Z",
  "MaxLength": 0,
  "Tags": [
    "scenario-common"
  ],
  "Flags": [],
  "Variables": [
    {
      "Id": "00a5cba7-6833-49cf-a7f5-9d478173117c",
      "Name": "AppGamebook",
      "Type": "EnumString",
      "EnumId": "0e37c09d-8583-4f73-be91-dea8208395cb",
      "DefaultPreviewValue": "0"
    }
  ],
  "Translations": [
    {
      "LanguageId": "en-US",
      "BaseTextHash": "92b417905d171b2dac1c140073622019ce4d73e53f82cf91c80cb833adcd3c15",
      "Text": "{AppGamebook:choose(App|Gamebook):Three Players|For Three Players}",
      "Status": "Approved",
      "SourceChanged": false,
      "UpdatedAt": "2026-07-13T20:00:11.1078848Z",
      "Suggestions": []
    }
  ]
}